gias2/__init__.py
gias2/version.py
gias2/applications/__init__.py
gias2/applications/giashmfinp2surf.py
gias2/applications/giasinpsampledicom.py
gias2/applications/giaspcreg.py
gias2/applications/giasrbfreg.py
gias2/applications/giasrigidreg.py
gias2/applications/giassurfacedistance.py
gias2/applications/giastrainpcashapemodel.py
gias2/common/__init__.py
gias2/common/geoprimitives.py
gias2/common/math.py
gias2/common/misc.py
gias2/common/tabledata.py
gias2/common/transform3D.py
gias2/examples/ASM_profile_matching.py
gias2/examples/HRV.py
gias2/examples/HRV_single_image_params_test.py
gias2/examples/STL_nearest_distance.py
gias2/examples/__init__.py
gias2/examples/csgcup.py
gias2/examples/giasrbfreg_config.ini
gias2/examples/hmf_inp_2_surf.py
gias2/examples/hmf_mat_map_inp.py
gias2/examples/inp_read_write.py
gias2/examples/inp_sample_dicom.py
gias2/examples/inp_sample_dicom_params.ini
gias2/examples/integral_image_cython.py
gias2/examples/modelio.py
gias2/examples/surface_to_surface_distance.py
gias2/examples/tetgen_meshes.py
gias2/examples/view_fieldwork_model_elements.py
gias2/examples/view_fieldwork_model_elements_script.py
gias2/examples/view_fieldwork_pca.py
gias2/examples/vtk_read_write.py
gias2/examples/data/2008_1741_tibia_fibula.wrl
gias2/examples/data/BN00104_E14727_S01_mc1 4_001.wrl
gias2/examples/data/autoCarpal1_outer.stl
gias2/examples/data/hip_test_image.npy
gias2/examples/data/manualCarpal1.stl
gias2/examples/data/prox_femur.inp
gias2/examples/data/prox_femur_out.inp
gias2/examples/data/tibia_left.ens
gias2/examples/data/tibia_left.geof
gias2/examples/data/tibia_left.mesh
gias2/examples/data/tibia_morphed.stl
gias2/examples/data/tibia_surface.stl
gias2/examples/data/tibia_volume.inp
gias2/examples/data/femur_pca/femur_left_mean_rigid_LLP26.geof
gias2/examples/data/femur_pca/femur_left_quartic_flat.ens
gias2/examples/data/femur_pca/femur_left_quartic_flat.mesh
gias2/examples/data/femur_pca/femur_left_rigid_LLP26.pc
gias2-0.7.14.dist-info/LICENSE
gias2-0.7.14.dist-info/METADATA
gias2-0.7.14.dist-info/WHEEL
gias2-0.7.14.dist-info/entry_points.txt
gias2-0.7.14.dist-info/top_level.txt
gias2-0.7.14.dist-info/RECORD
