Metadata-Version: 2.1
Name: gias2
Version: 0.7.14
Summary: A library of musculoskeletal modelling tools.
Home-page: https://bitbucket.org/jangle/gias2
Author: MAP Client Developers
License: mozilla
Keywords: musculoskeletal map mapclient
Platform: UNKNOWN
Classifier: Development Status :: 3 - Alpha
Classifier: License :: OSI Approved :: Mozilla Public License 2.0 (MPL 2.0)
Classifier: Programming Language :: Python :: 2.7
Classifier: Programming Language :: Python :: 3.5
Classifier: Topic :: Scientific/Engineering :: Medical Science Apps.
License-File: LICENSE
Requires-Dist: numpy (==1.19.5)
Requires-Dist: scipy (>=1.4.1)
Requires-Dist: scikit-learn (>=0.22.2)
Requires-Dist: scikit-image (>=0.16.2)
Requires-Dist: cython (>=0.29.16)
Requires-Dist: pydicom (>=1.4.2)
Requires-Dist: vtk (>=8.1.2)
Requires-Dist: configparser
